{
  "full": {
    "благодарю": "шакран",
    "блять": "алькир",
    "блядь": "алькир",
    "больно": "юдхи",
    "брат": "акха",
    "братья": "алихху",
    "в": "фи",
    "вода": "мау",
    "воды": "мау",
    "война": "харб",
    "герцог": "султан",
    "герцогу": "султану",
    "говно": "алькир",
    "год": "сана",
    "годы": "синин",
    "господин": "саид",
    "госпожа": "сайдати",
    "град": "полис",
    "город": "полис",
    "града": "полиса",
    "города": "полиса",
    "да": "на'ам",
    "демон": "шайтан",
    "демоны": "шайтаны",
    "день": "йом",
    "деньги": "мал",
    "дерьмо": "алькир",
    "девушка": "фата",
    "девушки": "фатаят",
    "дни": "айам",
    "долина": "вади",
    "до свидания": "андио",
    "друг": "садику",
    "друзья": "асдику",
    "еда": "тахам",
    "еды": "тахам",
    "заблуждение": "альвахм",
    "забудь": "янса",
    "замок": "кастро",
    "забытая": "манси",
    "здравствуйте": "хайре",
    "клинок": "шафратун",
    "козел": "маазу",
    "козлы": "альмаазу",
    "колдовство": "альсихр",
    "король": "султан",
    "королю": "султану",
    "кот": "кита",
    "котёнок": "ки'ти",
    "коты": "аль'киту",
    "котята": "аль'киту",
    "крепость": "кастро",
    "кровь": "дам",
    "крови": "дам",
    "лес": "габатун",
    "лич": "азиф",
    "лича": "азифу",
    "магия": "сихр",
    "мальчик": "валад",
    "мальчики": "алиад",
    "месяц": "шахр",
    "месяцы": "шухур",
    "меч": "сайф",
    "мой": "ли",
    "моя": "ли",
    "моё": "ли",
    "мои": "ли",
    "мрак": "альзалам",
    "мразь": "хутхала",
    "мрази": "хатали",
    "мужчина": "раджул",
    "мужчины": "риджал",
    "неделя": "усбу",
    "недели": "асабея",
    "нежить": "увнда",
    "нет": "ль'е",
    "ночь": "лейла",
    "ночи": "алайали",
    "отлично": "альзимун",
    "падение": "яскутун",
    "пизда": "куса",
    "пизды": "куса",
    "плачь": "ябки",
    "плохо": "бишакли",
    "пожалуйста": "пароколо",
    "помоги": "юсаид",
    "проклятие": "ланатун",
    "прощай": "ясу",
    "пока": "ясу",
    "прошу": "ласамахт",
    "привет": "хайре",
    "приветствую": "хайре",
    "работа": "вазифа",
    "работы": "амаль",
    "рыцарь": "фарис",
    "сестра": "ухти",
    "сестры": "альахават",
    "смерть": "муту",
    "смерти": "муту",
    "смешно": "мудхак",
    "собака": "кальб",
    "собаки": "килаб",
    "солнце": "шамс",
    "солнца": "шамс",
    "спасибо": "шукран",
    "страх": "якфату",
    "судьба": "кадару",
    "сука": "ахира",
    "суки": "алькальба",
    "темнота": "альзалам",
    "тень": "зуль",
    "ублюдок": "надлю",
    "ублюдки": "альаухадлю",
    "увидимся": "аруклакан",
    "хорошо": "агатос",
    "хуй": "кадибу",
    "хуи": "кадибу",
    "цветок": "варада",
    "цветы": "захуру",
    "церковь": "экклисия",
    "женщина": "имраа",
    "женщины": "ниса",
    "шлюха": "ахира",
    "это": "хаза",
    "баота": "Аль-Силат",
    "баоте": "Аль-Силат",
    "баоту": "Аль-Силат",
    "граггар": "Аль-Гуль",
    "граггару": "Аль-Гулю",
    "даэ": "йом",
    "дэц": "усбу",
    "дэцей": "асабея",
    "йилл": "сана",
    "йиллов": "синин",
    "маттиос": "Аль-Шайтан",
    "маттиосу": "Аль-Шайтану",
    "псайдон": "Аль-Псилла",
    "псайдону": "Аль-Псилле",
    "псайдоне": "Аль-Псилле"
    },
    "start": {
    },
    "end": {
    },
    "syllable": {

    }
}
